mcp_documentation_server/__init__.py
mcp_documentation_server/document_manager.py
mcp_documentation_server/install.py
mcp_documentation_server/launcher.py
mcp_documentation_server/search_engine.py
mcp_documentation_server/server.py
mcp_documentation_server/test_advanced.py
mcp_documentation_server/test_client.py
mcp_documentation_server/test_direct.py
mcp_documentation_server/test_quick.py
mcp_documentation_server-0.1.0.dist-info/licenses/LICENSE
mcp_documentation_server-0.1.0.dist-info/METADATA
mcp_documentation_server-0.1.0.dist-info/WHEEL
mcp_documentation_server-0.1.0.dist-info/entry_points.txt
mcp_documentation_server-0.1.0.dist-info/top_level.txt
mcp_documentation_server-0.1.0.dist-info/RECORD
