Metadata-Version: 2.4
Name: mcp-documentation-server
Version: 0.1.0
Summary: A FastMCP server for semantic search over technical documentation (.txt, .md files)
Author-email: Developer <dev@example.com>
License: MIT
Project-URL: Homepage, https://github.com/your-username/mcp-documentation-server
Project-URL: Repository, https://github.com/your-username/mcp-documentation-server
Project-URL: Issues, https://github.com/your-username/mcp-documentation-server/issues
Project-URL: Documentation, https://github.com/your-username/mcp-documentation-server#readme
Keywords: mcp,documentation,semantic-search,fastmcp,embeddings
Classifier: Development Status :: 4 - Beta
Classifier: Intended Audience :: Developers
Classifier: License :: OSI Approved :: MIT License
Classifier: Operating System :: OS Independent
Classifier: Programming Language :: Python :: 3
Classifier: Programming Language :: Python :: 3.8
Classifier: Programming Language :: Python :: 3.9
Classifier: Programming Language :: Python :: 3.10
Classifier: Programming Language :: Python :: 3.11
Classifier: Programming Language :: Python :: 3.12
Classifier: Topic :: Software Development :: Libraries :: Python Modules
Classifier: Topic :: Text Processing :: General
Classifier: Topic :: Scientific/Engineering :: Information Analysis
Requires-Python: >=3.8
License-File: LICENSE
Requires-Dist: fastmcp>=0.1.0
Requires-Dist: sentence-transformers>=2.2.0
Requires-Dist: scikit-learn>=1.3.0
Requires-Dist: numpy>=1.21.0
Provides-Extra: dev
Requires-Dist: pytest>=7.0.0; extra == "dev"
Requires-Dist: black>=22.0.0; extra == "dev"
Requires-Dist: isort>=5.0.0; extra == "dev"
Requires-Dist: build>=0.10.0; extra == "dev"
Requires-Dist: twine>=4.0.0; extra == "dev"
Dynamic: license-file
